st_common_data/__init__.py
st_common_data/datum.py
st_common_data/pagination.py
st_common_data/auth/__init__.py
st_common_data/auth/apps.py
st_common_data/auth/django_auth.py
st_common_data/auth/fastapi_auth.py
st_common_data/auth/serializers.py
st_common_data/auth/urls.py
st_common_data/auth/views.py
st_common_data/trading_accounts/__init__.py
st_common_data/trading_accounts/models.py
st_common_data/trading_accounts/serializers.py
st_common_data/trading_accounts/urls.py
st_common_data/trading_accounts/views.py
st_common_data/trading_accounts/migrations/0001_initial.py
st_common_data/trading_accounts/migrations/0002_tradingaccount_first_user.py
st_common_data/trading_accounts/migrations/0003_tradingaccount_personal_status.py
st_common_data/trading_accounts/migrations/0004_tradingaccount_platform.py
st_common_data/trading_accounts/migrations/0005_tradingaccount_routing.py
st_common_data/trading_accounts/migrations/0006_tradingaccount_bp_active.py
st_common_data/trading_accounts/migrations/0007_alter_tradingaccount_status.py
st_common_data/trading_accounts/migrations/__init__.py
st_common_data/utils/__init__.py
st_common_data/utils/common.py
st_common_data-0.2.9.13.dist-info/LICENCE
st_common_data-0.2.9.13.dist-info/METADATA
st_common_data-0.2.9.13.dist-info/WHEEL
st_common_data-0.2.9.13.dist-info/top_level.txt
st_common_data-0.2.9.13.dist-info/RECORD
