Metadata-Version: 2.1
Name: st_common_data
Version: 0.2.9.13
Summary: Data that is used in different ST projects
Home-page: https://github.com/ivanovds/st_common_data
Author: Daniil Ivanov
Author-email: danil.98and@gmail.com
Project-URL: Bug Tracker, https://github.com/ivanovds/st_common_data/issues
Classifier: Programming Language :: Python :: 3
Classifier: Environment :: Web Environment
Classifier: License :: OSI Approved :: MIT License
Classifier: Operating System :: OS Independent
Requires-Python: >=3.6
License-File: LICENCE
